{"frames":{"btn_restart.png":{"frame":{"h":150,"idx":0,"w":178,"x":179,"y":0},"rotated":false,"sourceSize":{"h":150,"w":178},"spriteSourceSize":{"h":150,"w":178,"x":0,"y":0},"trimmed":false},"btn_start.png":{"frame":{"h":150,"idx":0,"w":178,"x":0,"y":0},"rotated":false,"sourceSize":{"h":150,"w":178},"spriteSourceSize":{"h":150,"w":178,"x":0,"y":0},"trimmed":false},"clip_number.png":{"frame":{"h":24,"idx":0,"w":178,"x":139,"y":445},"rotated":false,"sourceSize":{"h":24,"w":178},"spriteSourceSize":{"h":24,"w":178,"x":0,"y":0},"trimmed":false},"hammer.png":{"frame":{"h":77,"idx":0,"w":98,"x":112,"y":256},"rotated":false,"sourceSize":{"h":77,"w":98},"spriteSourceSize":{"h":77,"w":98,"x":0,"y":0},"trimmed":false},"mask-01.png":{"frame":{"h":46,"idx":0,"w":138,"x":211,"y":304},"rotated":false,"sourceSize":{"h":46,"w":138},"spriteSourceSize":{"h":46,"w":138,"x":0,"y":0},"trimmed":false},"mask-02.png":{"frame":{"h":46,"idx":0,"w":138,"x":0,"y":428},"rotated":false,"sourceSize":{"h":46,"w":138},"spriteSourceSize":{"h":46,"w":138,"x":0,"y":0},"trimmed":false},"mask-03.png":{"frame":{"h":46,"idx":0,"w":138,"x":139,"y":398},"rotated":false,"sourceSize":{"h":46,"w":138},"spriteSourceSize":{"h":46,"w":138,"x":0,"y":0},"trimmed":false},"mask-04.png":{"frame":{"h":46,"idx":0,"w":138,"x":278,"y":351},"rotated":false,"sourceSize":{"h":46,"w":138},"spriteSourceSize":{"h":46,"w":138,"x":0,"y":0},"trimmed":false},"mask-05.png":{"frame":{"h":46,"idx":0,"w":138,"x":0,"y":381},"rotated":false,"sourceSize":{"h":46,"w":138},"spriteSourceSize":{"h":46,"w":138,"x":0,"y":0},"trimmed":false},"mask-06.png":{"frame":{"h":46,"idx":0,"w":138,"x":139,"y":351},"rotated":false,"sourceSize":{"h":46,"w":138},"spriteSourceSize":{"h":46,"w":138,"x":0,"y":0},"trimmed":false},"mask-07.png":{"frame":{"h":46,"idx":0,"w":138,"x":350,"y":304},"rotated":false,"sourceSize":{"h":46,"w":138},"spriteSourceSize":{"h":46,"w":138,"x":0,"y":0},"trimmed":false},"mask-08.png":{"frame":{"h":46,"idx":0,"w":138,"x":0,"y":334},"rotated":false,"sourceSize":{"h":46,"w":138},"spriteSourceSize":{"h":46,"w":138,"x":0,"y":0},"trimmed":false},"mask-09.png":{"frame":{"h":46,"idx":0,"w":132,"x":278,"y":398},"rotated":false,"sourceSize":{"h":46,"w":132},"spriteSourceSize":{"h":46,"w":132,"x":0,"y":0},"trimmed":false},"mouse_hit_1.png":{"frame":{"h":104,"idx":0,"w":111,"x":358,"y":0},"rotated":false,"sourceSize":{"h":104,"w":111},"spriteSourceSize":{"h":104,"w":111,"x":0,"y":0},"trimmed":false},"mouse_hit_2.png":{"frame":{"h":104,"idx":0,"w":111,"x":319,"y":151},"rotated":false,"sourceSize":{"h":104,"w":111},"spriteSourceSize":{"h":104,"w":111,"x":0,"y":0},"trimmed":false},"mouse_normal_1.png":{"frame":{"h":104,"idx":0,"w":111,"x":0,"y":224},"rotated":false,"sourceSize":{"h":104,"w":111},"spriteSourceSize":{"h":104,"w":111,"x":0,"y":0},"trimmed":false},"mouse_normal_2.png":{"frame":{"h":104,"idx":0,"w":111,"x":207,"y":151},"rotated":false,"sourceSize":{"h":104,"w":111},"spriteSourceSize":{"h":104,"w":111,"x":0,"y":0},"trimmed":false},"overBg.png":{"frame":{"h":62,"idx":0,"w":62,"x":411,"y":398},"rotated":false,"sourceSize":{"h":62,"w":62},"spriteSourceSize":{"h":62,"w":62,"x":0,"y":0},"trimmed":false},"progress_time$bar.png":{"frame":{"h":23,"idx":0,"w":301,"x":211,"y":280},"rotated":false,"sourceSize":{"h":23,"w":301},"spriteSourceSize":{"h":23,"w":301,"x":0,"y":0},"trimmed":false},"progress_time.png":{"frame":{"h":23,"idx":0,"w":301,"x":211,"y":256},"rotated":false,"sourceSize":{"h":23,"w":301},"spriteSourceSize":{"h":23,"w":301,"x":0,"y":0},"trimmed":false},"score_1.png":{"frame":{"h":30,"idx":0,"w":86,"x":318,"y":445},"rotated":false,"sourceSize":{"h":30,"w":86},"spriteSourceSize":{"h":30,"w":86,"x":0,"y":0},"trimmed":false},"score_2.png":{"frame":{"h":30,"idx":0,"w":86,"x":112,"y":224},"rotated":false,"sourceSize":{"h":30,"w":86},"spriteSourceSize":{"h":30,"w":86,"x":0,"y":0},"trimmed":false},"total Score.png":{"frame":{"h":72,"idx":0,"w":206,"x":0,"y":151},"rotated":false,"sourceSize":{"h":72,"w":206},"spriteSourceSize":{"h":72,"w":206,"x":0,"y":0},"trimmed":false}},"meta":{"image":"ui.png","prefix":"ui/"}}